mwl_ipandas/__init__.py
mwl_ipandas/main.py
mwl_ipandas-0.1.1.dist-info/entry_points.txt
mwl_ipandas-0.1.1.dist-info/WHEEL
mwl_ipandas-0.1.1.dist-info/METADATA
mwl_ipandas-0.1.1.dist-info/RECORD
